setup.py
crater/__init__.py
crater/crater.py
crater/gen.py
crater/gitcrate.py
crater/lockfile.py
crater/log.py
crater/selfcrate.py
crater/tarcrate.py
crater.egg-info/PKG-INFO
crater.egg-info/SOURCES.txt
crater.egg-info/dependency_links.txt
crater.egg-info/entry_points.txt
crater.egg-info/requires.txt
crater.egg-info/top_level.txt
test/test.py