Metadata-Version: 1.0
Name: crater
Version: 0.6
Summary: A dependency management system
Home-page: https://github.com/avakar/crater
Author: Martin Vejnár
Author-email: vejnar.martin@gmail.com
License: MIT
Platform: UNKNOWN
